LICENSE
MANIFEST.in
README.md
scrapy.cfg
setup.cfg
setup.py
os_scrapy_rq_crawler/__init__.py
os_scrapy_rq_crawler/crawler.py
os_scrapy_rq_crawler/items.py
os_scrapy_rq_crawler/middlewares.py
os_scrapy_rq_crawler/pipelines.py
os_scrapy_rq_crawler/settings.py
os_scrapy_rq_crawler/upstream.py
os_scrapy_rq_crawler/utils.py
os_scrapy_rq_crawler.egg-info/PKG-INFO
os_scrapy_rq_crawler.egg-info/SOURCES.txt
os_scrapy_rq_crawler.egg-info/dependency_links.txt
os_scrapy_rq_crawler.egg-info/not-zip-safe
os_scrapy_rq_crawler.egg-info/requires.txt
os_scrapy_rq_crawler.egg-info/top_level.txt
os_scrapy_rq_crawler/asyncio/__init__.py
os_scrapy_rq_crawler/asyncio/downloader.py
os_scrapy_rq_crawler/asyncio/engine.py
os_scrapy_rq_crawler/asyncio/rq.py
os_scrapy_rq_crawler/asyncio/scheduler.py
os_scrapy_rq_crawler/spiders/__init__.py
requirements/requirements-lint.txt
requirements/requirements-test.txt
requirements/requirements.txt
tests/__init__.py
tests/test_scrapy_check.py